azure/iot/deviceupdate/__init__.py
azure/iot/deviceupdate/_client.py
azure/iot/deviceupdate/_configuration.py
azure/iot/deviceupdate/_patch.py
azure/iot/deviceupdate/_serialization.py
azure/iot/deviceupdate/_vendor.py
azure/iot/deviceupdate/_version.py
azure/iot/deviceupdate/py.typed
azure/iot/deviceupdate/aio/__init__.py
azure/iot/deviceupdate/aio/_client.py
azure/iot/deviceupdate/aio/_configuration.py
azure/iot/deviceupdate/aio/_patch.py
azure/iot/deviceupdate/aio/operations/__init__.py
azure/iot/deviceupdate/aio/operations/_operations.py
azure/iot/deviceupdate/aio/operations/_patch.py
azure/iot/deviceupdate/operations/__init__.py
azure/iot/deviceupdate/operations/_operations.py
azure/iot/deviceupdate/operations/_patch.py
azure_iot_deviceupdate-1.0.0.dist-info/LICENSE
azure_iot_deviceupdate-1.0.0.dist-info/METADATA
azure_iot_deviceupdate-1.0.0.dist-info/WHEEL
azure_iot_deviceupdate-1.0.0.dist-info/top_level.txt
azure_iot_deviceupdate-1.0.0.dist-info/RECORD
