Metadata-Version: 2.1
Name: azure-iot-deviceupdate
Version: 1.0.0
Summary: Microsoft Azure Device Update Client Library for Python
Home-page: https://github.com/Azure/azure-sdk-for-python/tree/main/sdk/deviceupdate/azure-iot-deviceupdate
Author: Microsoft Corporation
Author-email: adupmdevteam@microsoft.com
License: MIT License
Classifier: Development Status :: 4 - Beta
Classifier: Programming Language :: Python
Classifier: Programming Language :: Python :: 3 :: Only
Classifier: Programming Language :: Python :: 3
Classifier: Programming Language :: Python :: 3.6
Classifier: Programming Language :: Python :: 3.7
Classifier: Programming Language :: Python :: 3.8
Classifier: Programming Language :: Python :: 3.9
Classifier: Programming Language :: Python :: 3.10
Classifier: License :: OSI Approved :: MIT License
Requires-Python: >=3.6
License-File: LICENSE
Requires-Dist: isodate (<1.0.0,>=0.6.1)
Requires-Dist: azure-core (<2.0.0,>=1.24.0)
